<?xml version="1.0" encoding="utf-8" standalone="yes"?>
<root>
  <issues>
    <issue>
      <Name value="TBA" />
      <ID value="Booking process" />
    </issue>
    <issue>
      <Name value="TBA" />
      <ID value="Call center staff" />
    </issue>
    <issue>
      <Name value="TBA" />
      <ID value="Future travel" />
    </issue>
    <issue>
      <Name value="TBA" />
      <ID value="Policy" />
    </issue> 
    <issue>
      <Name value="TBA" />
      <ID value="Terms &amp; conditions" />
    </issue>
    <issue>
      <Name value="TBA" />
      <ID value="Voucher redemption online" />
    </issue>
    <issue>
      <Name value="TBA" />
      <ID value="Unable to check-in online" />
    </issue>
    <issue>
      <Name value="TBA" />
      <ID value="Website/mobile app funtionality" />
    </issue>
  </issues>
</root>
